audio_dspy/__init__.py
audio_dspy/adaptive_filt.py
audio_dspy/delay_utils.py
audio_dspy/eq.py
audio_dspy/eq_design.py
audio_dspy/farina.py
audio_dspy/level_detector.py
audio_dspy/modal_tools.py
audio_dspy/nonlinearities.py
audio_dspy/plotting.py
audio_dspy/prony.py
audio_dspy/sweeps.py
audio_dspy/transfer_function_tools.py
audio_dspy-0.0.4.dist-info/METADATA
audio_dspy-0.0.4.dist-info/RECORD
audio_dspy-0.0.4.dist-info/WHEEL
audio_dspy-0.0.4.dist-info/top_level.txt
benchmarks/__init__.py
benchmarks/eq_design_bench.py
benchmarks/nonlinearities_bench.py
benchmarks/prony_bench.py
benchmarks/sweeps_bench.py
benchmarks/transfer_functions_bench.py
tests/__init__.py
tests/test_adaptive_filt.py
tests/test_delay_utils.py
tests/test_eq.py
tests/test_eq_design.py
tests/test_farina.py
tests/test_level_detector.py
tests/test_modal.py
tests/test_nonlinearities.py
tests/test_prony.py
tests/test_sweeps.py
tests/test_tf.py
