Metadata-Version: 2.1
Name: audio_dspy
Version: 0.0.4
Summary: A package for audio DSP tools
Home-page: https://github.com/jatinchowdhury18/audio_dspy
Author: Jatin Chowdhury
Author-email: jatin@ccrma.stanford.edu
License: UNKNOWN
Platform: UNKNOWN
Classifier: Programming Language :: Python :: 3
Classifier: License :: OSI Approved :: MIT License
Classifier: Operating System :: OS Independent
Requires-Python: >=3.6
